<?xml version="1.0" encoding="UTF-8"?>
<!DOCTYPE mapper PUBLIC "-//mybatis.org//DTD Mapper 3.0//EN" "http://mybatis.org/dtd/mybatis-3-mapper.dtd">
<mapper namespace="com.skf.management.mapper.UserCustomerMapper">
  <resultMap id="BaseResultMap" type="com.skf.management.model.UserCustomerModelKey">
    <!--
      WARNING - @mbg.generated
      This element is automatically generated by MyBatis Generator, do not modify.
      This element was generated on Fri Jun 15 18:04:35 CST 2018.
    -->
    <id column="USR_CODE" jdbcType="VARCHAR" property="userCode" />
    <id column="CSTM_CODE" jdbcType="VARCHAR" property="customerCode" />
  </resultMap>
  <resultMap id="checkResultMap" type="com.skf.management.entity.UserCustomerEntity">
    <!--
      WARNING - @mbg.generated
      This element is automatically generated by MyBatis Generator, do not modify.
      This element was generated on Tue May 22 14:56:15 CST 2018.
    -->
    <id column="CSTM_CODE" jdbcType="VARCHAR" property="customerCode" />
    <id column="CSTM_NAME" jdbcType="VARCHAR" property="cstmName" />
    <id column="USR_CODE" jdbcType="VARCHAR" property="userCode" />
    <id column="ifChecked" jdbcType="VARCHAR" property="ifChecked" />
  </resultMap>
  <select id="selectByUserCode" parameterType="String" resultMap="checkResultMap">
    <!--
      add By  Jamie 20180608
    -->
    select 
		sc.CSTM_CODE as code,
		sc.CSTM_NAME as name,
		CASE WHEN 
			suc.USR_CODE is not NULL 
		then 
			'checked' 
		END as ifChecked 
	from 
		SKF_CSTM sc 
	left JOIN 
		SKF_USR_CSTM suc 
	on 
		sc.CSTM_CODE = suc.CSTM_CODE
	where 
		suc.USR_CODE=#{code}
  </select>
</mapper>